tests/__init__.py
tests/test_wizcon.py
wizcon/__init__.py
wizcon/test_wizcon.py
wizcon/wizcon.py
wizcon-0.3.0.dist-info/LICENSE.txt
wizcon-0.3.0.dist-info/METADATA
wizcon-0.3.0.dist-info/WHEEL
wizcon-0.3.0.dist-info/entry_points.txt
wizcon-0.3.0.dist-info/top_level.txt
wizcon-0.3.0.dist-info/RECORD
