Metadata-Version: 2.1
Name: wizcon
Version: 0.3.0
Summary: Control Philips WiZ Connected smart light bulbs
Home-page: https://github.com/rgomezjnr/wizcon
Author: Robert Gomez, Jr.
Author-email: rgomezjnr@gmail.com
License: MIT
Keywords: philips wiz wifi wireless home automation cli tool
Platform: UNKNOWN
Classifier: Programming Language :: Python :: 3
Classifier: Programming Language :: Python :: 3.6
Classifier: Programming Language :: Python :: 3.7
Classifier: Programming Language :: Python :: 3.8
Classifier: License :: OSI Approved :: MIT License
Classifier: Operating System :: OS Independent
Classifier: Development Status :: 4 - Beta
Classifier: Environment :: Console
Classifier: Intended Audience :: End Users/Desktop
Classifier: Topic :: Home Automation
Classifier: Topic :: Utilities
Requires-Python: >=3.6
Requires-Dist: pywizlight
